vector/__init__.py
vector/_methods.py
vector/_typeutils.py
vector/_version.py
vector/_version.pyi
vector/py.typed
vector/_compute/__init__.py
vector/_compute/lorentz/Et.py
vector/_compute/lorentz/Et2.py
vector/_compute/lorentz/Mt.py
vector/_compute/lorentz/Mt2.py
vector/_compute/lorentz/__init__.py
vector/_compute/lorentz/add.py
vector/_compute/lorentz/beta.py
vector/_compute/lorentz/boostX_beta.py
vector/_compute/lorentz/boostX_gamma.py
vector/_compute/lorentz/boostY_beta.py
vector/_compute/lorentz/boostY_gamma.py
vector/_compute/lorentz/boostZ_beta.py
vector/_compute/lorentz/boostZ_gamma.py
vector/_compute/lorentz/boost_beta3.py
vector/_compute/lorentz/boost_p4.py
vector/_compute/lorentz/deltaRapidityPhi.py
vector/_compute/lorentz/deltaRapidityPhi2.py
vector/_compute/lorentz/dot.py
vector/_compute/lorentz/equal.py
vector/_compute/lorentz/gamma.py
vector/_compute/lorentz/is_lightlike.py
vector/_compute/lorentz/is_spacelike.py
vector/_compute/lorentz/is_timelike.py
vector/_compute/lorentz/isclose.py
vector/_compute/lorentz/not_equal.py
vector/_compute/lorentz/rapidity.py
vector/_compute/lorentz/scale.py
vector/_compute/lorentz/subtract.py
vector/_compute/lorentz/t.py
vector/_compute/lorentz/t2.py
vector/_compute/lorentz/tau.py
vector/_compute/lorentz/tau2.py
vector/_compute/lorentz/to_beta3.py
vector/_compute/lorentz/transform4D.py
vector/_compute/lorentz/unit.py
vector/_compute/planar/__init__.py
vector/_compute/planar/add.py
vector/_compute/planar/deltaphi.py
vector/_compute/planar/dot.py
vector/_compute/planar/equal.py
vector/_compute/planar/is_antiparallel.py
vector/_compute/planar/is_parallel.py
vector/_compute/planar/is_perpendicular.py
vector/_compute/planar/isclose.py
vector/_compute/planar/not_equal.py
vector/_compute/planar/phi.py
vector/_compute/planar/rho.py
vector/_compute/planar/rho2.py
vector/_compute/planar/rotateZ.py
vector/_compute/planar/scale.py
vector/_compute/planar/subtract.py
vector/_compute/planar/transform2D.py
vector-1.6.3.dist-info/METADATA
vector-1.6.3.dist-info/WHEEL
vector-1.6.3.dist-info/entry_points.txt
vector-1.6.3.dist-info/licenses/LICENSE
vector-1.6.3.dist-info/RECORD
